Classfile /D:/Tutorials/SpringBoot/Microservices-Kafka/device-service/target/classes/com/smtech/device_service/controller/DeviceController.class
  Last modified May 7, 2026; size 3703 bytes
  SHA-256 checksum b0576d802df47ae0abf7af39c9b439e4403afe30d0307500024bf631e66edbd7
  Compiled from "DeviceController.java"
public class com.smtech.device_service.controller.DeviceController
  minor version: 0
  major version: 65
  flags: (0x0021) ACC_PUBLIC, ACC_SUPER
  this_class: #8                          // com/smtech/device_service/controller/DeviceController
  super_class: #2                         // java/lang/Object
  interfaces: 0, fields: 2, methods: 5, attributes: 3
Constant pool:
    #1 = Methodref          #2.#3         // java/lang/Object."<init>":()V
    #2 = Class              #4            // java/lang/Object
    #3 = NameAndType        #5:#6         // "<init>":()V
    #4 = Utf8               java/lang/Object
    #5 = Utf8               <init>
    #6 = Utf8               ()V
    #7 = Fieldref           #8.#9         // com/smtech/device_service/controller/DeviceController.deviceService:Lcom/smtech/device_service/service/DeviceService;
    #8 = Class              #10           // com/smtech/device_service/controller/DeviceController
    #9 = NameAndType        #11:#12       // deviceService:Lcom/smtech/device_service/service/DeviceService;
   #10 = Utf8               com/smtech/device_service/controller/DeviceController
   #11 = Utf8               deviceService
   #12 = Utf8               Lcom/smtech/device_service/service/DeviceService;
   #13 = Methodref          #14.#15       // com/smtech/device_service/service/DeviceService.getDeviceById:(Ljava/lang/Long;)Lcom/smtech/device_service/dto/DeviceDto;
   #14 = Class              #16           // com/smtech/device_service/service/DeviceService
   #15 = NameAndType        #17:#18       // getDeviceById:(Ljava/lang/Long;)Lcom/smtech/device_service/dto/DeviceDto;
   #16 = Utf8               com/smtech/device_service/service/DeviceService
   #17 = Utf8               getDeviceById
   #18 = Utf8               (Ljava/lang/Long;)Lcom/smtech/device_service/dto/DeviceDto;
   #19 = Methodref          #20.#21       // org/springframework/http/ResponseEntity.ok:(Ljava/lang/Object;)Lorg/springframework/http/ResponseEntity;
   #20 = Class              #22           // org/springframework/http/ResponseEntity
   #21 = NameAndType        #23:#24       // ok:(Ljava/lang/Object;)Lorg/springframework/http/ResponseEntity;
   #22 = Utf8               org/springframework/http/ResponseEntity
   #23 = Utf8               ok
   #24 = Utf8               (Ljava/lang/Object;)Lorg/springframework/http/ResponseEntity;
   #25 = Methodref          #14.#26       // com/smtech/device_service/service/DeviceService.createDevice:(Lcom/smtech/device_service/dto/DeviceDto;)Lcom/smtech/device_service/dto/DeviceDto;
   #26 = NameAndType        #27:#28       // createDevice:(Lcom/smtech/device_service/dto/DeviceDto;)Lcom/smtech/device_service/dto/DeviceDto;
   #27 = Utf8               createDevice
   #28 = Utf8               (Lcom/smtech/device_service/dto/DeviceDto;)Lcom/smtech/device_service/dto/DeviceDto;
   #29 = Fieldref           #30.#31       // org/springframework/http/HttpStatus.CREATED:Lorg/springframework/http/HttpStatus;
   #30 = Class              #32           // org/springframework/http/HttpStatus
   #31 = NameAndType        #33:#34       // CREATED:Lorg/springframework/http/HttpStatus;
   #32 = Utf8               org/springframework/http/HttpStatus
   #33 = Utf8               CREATED
   #34 = Utf8               Lorg/springframework/http/HttpStatus;
   #35 = Methodref          #20.#36       // org/springframework/http/ResponseEntity.status:(Lorg/springframework/http/HttpStatusCode;)Lorg/springframework/http/ResponseEntity$BodyBuilder;
   #36 = NameAndType        #37:#38       // status:(Lorg/springframework/http/HttpStatusCode;)Lorg/springframework/http/ResponseEntity$BodyBuilder;
   #37 = Utf8               status
   #38 = Utf8               (Lorg/springframework/http/HttpStatusCode;)Lorg/springframework/http/ResponseEntity$BodyBuilder;
   #39 = InterfaceMethodref #40.#41       // org/springframework/http/ResponseEntity$BodyBuilder.body:(Ljava/lang/Object;)Lorg/springframework/http/ResponseEntity;
   #40 = Class              #42           // org/springframework/http/ResponseEntity$BodyBuilder
   #41 = NameAndType        #43:#24       // body:(Ljava/lang/Object;)Lorg/springframework/http/ResponseEntity;
   #42 = Utf8               org/springframework/http/ResponseEntity$BodyBuilder
   #43 = Utf8               body
   #44 = Methodref          #14.#45       // com/smtech/device_service/service/DeviceService.updateDevice:(Ljava/lang/Long;Lcom/smtech/device_service/dto/DeviceDto;)Lcom/smtech/device_service/dto/DeviceDto;
   #45 = NameAndType        #46:#47       // updateDevice:(Ljava/lang/Long;Lcom/smtech/device_service/dto/DeviceDto;)Lcom/smtech/device_service/dto/DeviceDto;
   #46 = Utf8               updateDevice
   #47 = Utf8               (Ljava/lang/Long;Lcom/smtech/device_service/dto/DeviceDto;)Lcom/smtech/device_service/dto/DeviceDto;
   #48 = Methodref          #20.#49       // org/springframework/http/ResponseEntity.notFound:()Lorg/springframework/http/ResponseEntity$HeadersBuilder;
   #49 = NameAndType        #50:#51       // notFound:()Lorg/springframework/http/ResponseEntity$HeadersBuilder;
   #50 = Utf8               notFound
   #51 = Utf8               ()Lorg/springframework/http/ResponseEntity$HeadersBuilder;
   #52 = InterfaceMethodref #53.#54       // org/springframework/http/ResponseEntity$HeadersBuilder.build:()Lorg/springframework/http/ResponseEntity;
   #53 = Class              #55           // org/springframework/http/ResponseEntity$HeadersBuilder
   #54 = NameAndType        #56:#57       // build:()Lorg/springframework/http/ResponseEntity;
   #55 = Utf8               org/springframework/http/ResponseEntity$HeadersBuilder
   #56 = Utf8               build
   #57 = Utf8               ()Lorg/springframework/http/ResponseEntity;
   #58 = Methodref          #59.#60       // org/slf4j/LoggerFactory.getLogger:(Ljava/lang/Class;)Lorg/slf4j/Logger;
   #59 = Class              #61           // org/slf4j/LoggerFactory
   #60 = NameAndType        #62:#63       // getLogger:(Ljava/lang/Class;)Lorg/slf4j/Logger;
   #61 = Utf8               org/slf4j/LoggerFactory
   #62 = Utf8               getLogger
   #63 = Utf8               (Ljava/lang/Class;)Lorg/slf4j/Logger;
   #64 = Fieldref           #8.#65        // com/smtech/device_service/controller/DeviceController.log:Lorg/slf4j/Logger;
   #65 = NameAndType        #66:#67       // log:Lorg/slf4j/Logger;
   #66 = Utf8               log
   #67 = Utf8               Lorg/slf4j/Logger;
   #68 = Utf8               RuntimeInvisibleAnnotations
   #69 = Utf8               Llombok/Generated;
   #70 = Utf8               (Lcom/smtech/device_service/service/DeviceService;)V
   #71 = Utf8               Code
   #72 = Utf8               LineNumberTable
   #73 = Utf8               LocalVariableTable
   #74 = Utf8               this
   #75 = Utf8               Lcom/smtech/device_service/controller/DeviceController;
   #76 = Utf8               MethodParameters
   #77 = Utf8               (Ljava/lang/Long;)Lorg/springframework/http/ResponseEntity;
   #78 = Utf8               id
   #79 = Utf8               Ljava/lang/Long;
   #80 = Utf8               deviceDto
   #81 = Utf8               Lcom/smtech/device_service/dto/DeviceDto;
   #82 = Utf8               Signature
   #83 = Utf8               (Ljava/lang/Long;)Lorg/springframework/http/ResponseEntity<Lcom/smtech/device_service/dto/DeviceDto;>;
   #84 = Utf8               RuntimeVisibleAnnotations
   #85 = Utf8               Lorg/springframework/web/bind/annotation/GetMapping;
   #86 = Utf8               value
   #87 = Utf8               /{id}
   #88 = Utf8               RuntimeVisibleParameterAnnotations
   #89 = Utf8               Lorg/springframework/web/bind/annotation/PathVariable;
   #90 = Utf8               (Lcom/smtech/device_service/dto/DeviceDto;)Lorg/springframework/http/ResponseEntity;
   #91 = Utf8               createdDevice
   #92 = Utf8               (Lcom/smtech/device_service/dto/DeviceDto;)Lorg/springframework/http/ResponseEntity<Lcom/smtech/device_service/dto/DeviceDto;>;
   #93 = Utf8               Lorg/springframework/web/bind/annotation/PostMapping;
   #94 = Utf8               Lorg/springframework/web/bind/annotation/RequestBody;
   #95 = Utf8               (Ljava/lang/Long;Lcom/smtech/device_service/dto/DeviceDto;)Lorg/springframework/http/ResponseEntity;
   #96 = Utf8               updatedDevice
   #97 = Utf8               StackMapTable
   #98 = Class              #99           // com/smtech/device_service/dto/DeviceDto
   #99 = Utf8               com/smtech/device_service/dto/DeviceDto
  #100 = Utf8               (Ljava/lang/Long;Lcom/smtech/device_service/dto/DeviceDto;)Lorg/springframework/http/ResponseEntity<Lcom/smtech/device_service/dto/DeviceDto;>;
  #101 = Utf8               Lorg/springframework/web/bind/annotation/PutMapping;
  #102 = Utf8               <clinit>
  #103 = Utf8               SourceFile
  #104 = Utf8               DeviceController.java
  #105 = Utf8               Lorg/springframework/web/bind/annotation/RestController;
  #106 = Utf8               Lorg/springframework/web/bind/annotation/RequestMapping;
  #107 = Utf8               /api/v1/device
  #108 = Utf8               InnerClasses
  #109 = Utf8               BodyBuilder
  #110 = Utf8               HeadersBuilder
{
  public com.smtech.device_service.controller.DeviceController(com.smtech.device_service.service.DeviceService);
    descriptor: (Lcom/smtech/device_service/service/DeviceService;)V
    flags: (0x0001) ACC_PUBLIC
    Code:
      stack=2, locals=2, args_size=2
         0: aload_0
         1: invokespecial #1                  // Method java/lang/Object."<init>":()V
         4: aload_0
         5: aload_1
         6: putfield      #7                  // Field deviceService:Lcom/smtech/device_service/service/DeviceService;
         9: return
      LineNumberTable:
        line 27: 0
        line 28: 4
        line 29: 9
      LocalVariableTable:
        Start  Length  Slot  Name   Signature
            0      10     0  this   Lcom/smtech/device_service/controller/DeviceController;
            0      10     1 deviceService   Lcom/smtech/device_service/service/DeviceService;
    MethodParameters:
      Name                           Flags
      deviceService

  public org.springframework.http.ResponseEntity<com.smtech.device_service.dto.DeviceDto> getDeviceById(java.lang.Long);
    descriptor: (Ljava/lang/Long;)Lorg/springframework/http/ResponseEntity;
    flags: (0x0001) ACC_PUBLIC
    Code:
      stack=2, locals=3, args_size=2
         0: aload_0
         1: getfield      #7                  // Field deviceService:Lcom/smtech/device_service/service/DeviceService;
         4: aload_1
         5: invokevirtual #13                 // Method com/smtech/device_service/service/DeviceService.getDeviceById:(Ljava/lang/Long;)Lcom/smtech/device_service/dto/DeviceDto;
         8: astore_2
         9: aload_2
        10: invokestatic  #19                 // Method org/springframework/http/ResponseEntity.ok:(Ljava/lang/Object;)Lorg/springframework/http/ResponseEntity;
        13: areturn
      LineNumberTable:
        line 33: 0
        line 34: 9
      LocalVariableTable:
        Start  Length  Slot  Name   Signature
            0      14     0  this   Lcom/smtech/device_service/controller/DeviceController;
            0      14     1    id   Ljava/lang/Long;
            9       5     2 deviceDto   Lcom/smtech/device_service/dto/DeviceDto;
    MethodParameters:
      Name                           Flags
      id
    Signature: #83                          // (Ljava/lang/Long;)Lorg/springframework/http/ResponseEntity<Lcom/smtech/device_service/dto/DeviceDto;>;
    RuntimeVisibleAnnotations:
      0: #85(#86=[s#87])
        org.springframework.web.bind.annotation.GetMapping(
          value=["/{id}"]
        )
    RuntimeVisibleParameterAnnotations:
      parameter 0:
        0: #89()
          org.springframework.web.bind.annotation.PathVariable

  public org.springframework.http.ResponseEntity<com.smtech.device_service.dto.DeviceDto> createDevice(com.smtech.device_service.dto.DeviceDto);
    descriptor: (Lcom/smtech/device_service/dto/DeviceDto;)Lorg/springframework/http/ResponseEntity;
    flags: (0x0001) ACC_PUBLIC
    Code:
      stack=2, locals=3, args_size=2
         0: aload_0
         1: getfield      #7                  // Field deviceService:Lcom/smtech/device_service/service/DeviceService;
         4: aload_1
         5: invokevirtual #25                 // Method com/smtech/device_service/service/DeviceService.createDevice:(Lcom/smtech/device_service/dto/DeviceDto;)Lcom/smtech/device_service/dto/DeviceDto;
         8: astore_2
         9: getstatic     #29                 // Field org/springframework/http/HttpStatus.CREATED:Lorg/springframework/http/HttpStatus;
        12: invokestatic  #35                 // Method org/springframework/http/ResponseEntity.status:(Lorg/springframework/http/HttpStatusCode;)Lorg/springframework/http/ResponseEntity$BodyBuilder;
        15: aload_2
        16: invokeinterface #39,  2           // InterfaceMethod org/springframework/http/ResponseEntity$BodyBuilder.body:(Ljava/lang/Object;)Lorg/springframework/http/ResponseEntity;
        21: areturn
      LineNumberTable:
        line 39: 0
        line 40: 9
      LocalVariableTable:
        Start  Length  Slot  Name   Signature
            0      22     0  this   Lcom/smtech/device_service/controller/DeviceController;
            0      22     1 deviceDto   Lcom/smtech/device_service/dto/DeviceDto;
            9      13     2 createdDevice   Lcom/smtech/device_service/dto/DeviceDto;
    MethodParameters:
      Name                           Flags
      deviceDto
    Signature: #92                          // (Lcom/smtech/device_service/dto/DeviceDto;)Lorg/springframework/http/ResponseEntity<Lcom/smtech/device_service/dto/DeviceDto;>;
    RuntimeVisibleAnnotations:
      0: #93()
        org.springframework.web.bind.annotation.PostMapping
    RuntimeVisibleParameterAnnotations:
      parameter 0:
        0: #94()
          org.springframework.web.bind.annotation.RequestBody

  public org.springframework.http.ResponseEntity<com.smtech.device_service.dto.DeviceDto> updateDevice(java.lang.Long, com.smtech.device_service.dto.DeviceDto);
    descriptor: (Ljava/lang/Long;Lcom/smtech/device_service/dto/DeviceDto;)Lorg/springframework/http/ResponseEntity;
    flags: (0x0001) ACC_PUBLIC
    Code:
      stack=3, locals=4, args_size=3
         0: aload_0
         1: getfield      #7                  // Field deviceService:Lcom/smtech/device_service/service/DeviceService;
         4: aload_1
         5: aload_2
         6: invokevirtual #44                 // Method com/smtech/device_service/service/DeviceService.updateDevice:(Ljava/lang/Long;Lcom/smtech/device_service/dto/DeviceDto;)Lcom/smtech/device_service/dto/DeviceDto;
         9: astore_3
        10: aload_3
        11: ifnonnull     23
        14: invokestatic  #48                 // Method org/springframework/http/ResponseEntity.notFound:()Lorg/springframework/http/ResponseEntity$HeadersBuilder;
        17: invokeinterface #52,  1           // InterfaceMethod org/springframework/http/ResponseEntity$HeadersBuilder.build:()Lorg/springframework/http/ResponseEntity;
        22: areturn
        23: aload_3
        24: invokestatic  #19                 // Method org/springframework/http/ResponseEntity.ok:(Ljava/lang/Object;)Lorg/springframework/http/ResponseEntity;
        27: areturn
      LineNumberTable:
        line 45: 0
        line 46: 10
        line 47: 14
        line 50: 23
      LocalVariableTable:
        Start  Length  Slot  Name   Signature
            0      28     0  this   Lcom/smtech/device_service/controller/DeviceController;
            0      28     1    id   Ljava/lang/Long;
            0      28     2 deviceDto   Lcom/smtech/device_service/dto/DeviceDto;
           10      18     3 updatedDevice   Lcom/smtech/device_service/dto/DeviceDto;
      StackMapTable: number_of_entries = 1
        frame_type = 252 /* append */
          offset_delta = 23
          locals = [ class com/smtech/device_service/dto/DeviceDto ]
    MethodParameters:
      Name                           Flags
      id
      deviceDto
    Signature: #100                         // (Ljava/lang/Long;Lcom/smtech/device_service/dto/DeviceDto;)Lorg/springframework/http/ResponseEntity<Lcom/smtech/device_service/dto/DeviceDto;>;
    RuntimeVisibleAnnotations:
      0: #101(#86=[s#87])
        org.springframework.web.bind.annotation.PutMapping(
          value=["/{id}"]
        )
    RuntimeVisibleParameterAnnotations:
      parameter 0:
        0: #89()
          org.springframework.web.bind.annotation.PathVariable
      parameter 1:
        0: #94()
          org.springframework.web.bind.annotation.RequestBody

  static {};
    descriptor: ()V
    flags: (0x0008) ACC_STATIC
    Code:
      stack=1, locals=0, args_size=0
         0: ldc           #8                  // class com/smtech/device_service/controller/DeviceController
         2: invokestatic  #58                 // Method org/slf4j/LoggerFactory.getLogger:(Ljava/lang/Class;)Lorg/slf4j/Logger;
         5: putstatic     #64                 // Field log:Lorg/slf4j/Logger;
         8: return
      LineNumberTable:
        line 22: 0
}
SourceFile: "DeviceController.java"
RuntimeVisibleAnnotations:
  0: #105()
    org.springframework.web.bind.annotation.RestController
  1: #106(#86=[s#107])
    org.springframework.web.bind.annotation.RequestMapping(
      value=["/api/v1/device"]
    )
InnerClasses:
  public static #109= #40 of #20;         // BodyBuilder=class org/springframework/http/ResponseEntity$BodyBuilder of class org/springframework/http/ResponseEntity
  public static #110= #53 of #20;         // HeadersBuilder=class org/springframework/http/ResponseEntity$HeadersBuilder of class org/springframework/http/ResponseEntity
