Classfile /D:/Tutorials/SpringBoot/Microservices-Kafka/user-service/target/classes/com/smtech/user_service/controller/UserController.class
  Last modified May 7, 2026; size 3791 bytes
  SHA-256 checksum d75bb1f14802b68731e3eaebb475cf3997bbe24b29099bab41b9f0b04e6863f6
  Compiled from "UserController.java"
public class com.smtech.user_service.controller.UserController
  minor version: 0
  major version: 65
  flags: (0x0021) ACC_PUBLIC, ACC_SUPER
  this_class: #8                          // com/smtech/user_service/controller/UserController
  super_class: #2                         // java/lang/Object
  interfaces: 0, fields: 1, methods: 5, attributes: 3
Constant pool:
    #1 = Methodref          #2.#3         // java/lang/Object."<init>":()V
    #2 = Class              #4            // java/lang/Object
    #3 = NameAndType        #5:#6         // "<init>":()V
    #4 = Utf8               java/lang/Object
    #5 = Utf8               <init>
    #6 = Utf8               ()V
    #7 = Fieldref           #8.#9         // com/smtech/user_service/controller/UserController.userService:Lcom/smtech/user_service/service/UserService;
    #8 = Class              #10           // com/smtech/user_service/controller/UserController
    #9 = NameAndType        #11:#12       // userService:Lcom/smtech/user_service/service/UserService;
   #10 = Utf8               com/smtech/user_service/controller/UserController
   #11 = Utf8               userService
   #12 = Utf8               Lcom/smtech/user_service/service/UserService;
   #13 = Methodref          #14.#15       // com/smtech/user_service/service/UserService.createUser:(Lcom/smtech/user_service/dto/UserDto;)Lcom/smtech/user_service/dto/UserDto;
   #14 = Class              #16           // com/smtech/user_service/service/UserService
   #15 = NameAndType        #17:#18       // createUser:(Lcom/smtech/user_service/dto/UserDto;)Lcom/smtech/user_service/dto/UserDto;
   #16 = Utf8               com/smtech/user_service/service/UserService
   #17 = Utf8               createUser
   #18 = Utf8               (Lcom/smtech/user_service/dto/UserDto;)Lcom/smtech/user_service/dto/UserDto;
   #19 = Fieldref           #20.#21       // org/springframework/http/HttpStatus.CREATED:Lorg/springframework/http/HttpStatus;
   #20 = Class              #22           // org/springframework/http/HttpStatus
   #21 = NameAndType        #23:#24       // CREATED:Lorg/springframework/http/HttpStatus;
   #22 = Utf8               org/springframework/http/HttpStatus
   #23 = Utf8               CREATED
   #24 = Utf8               Lorg/springframework/http/HttpStatus;
   #25 = Methodref          #26.#27       // org/springframework/http/ResponseEntity.status:(Lorg/springframework/http/HttpStatusCode;)Lorg/springframework/http/ResponseEntity$BodyBuilder;
   #26 = Class              #28           // org/springframework/http/ResponseEntity
   #27 = NameAndType        #29:#30       // status:(Lorg/springframework/http/HttpStatusCode;)Lorg/springframework/http/ResponseEntity$BodyBuilder;
   #28 = Utf8               org/springframework/http/ResponseEntity
   #29 = Utf8               status
   #30 = Utf8               (Lorg/springframework/http/HttpStatusCode;)Lorg/springframework/http/ResponseEntity$BodyBuilder;
   #31 = InterfaceMethodref #32.#33       // org/springframework/http/ResponseEntity$BodyBuilder.body:(Ljava/lang/Object;)Lorg/springframework/http/ResponseEntity;
   #32 = Class              #34           // org/springframework/http/ResponseEntity$BodyBuilder
   #33 = NameAndType        #35:#36       // body:(Ljava/lang/Object;)Lorg/springframework/http/ResponseEntity;
   #34 = Utf8               org/springframework/http/ResponseEntity$BodyBuilder
   #35 = Utf8               body
   #36 = Utf8               (Ljava/lang/Object;)Lorg/springframework/http/ResponseEntity;
   #37 = Methodref          #14.#38       // com/smtech/user_service/service/UserService.getUserById:(Ljava/lang/Long;)Lcom/smtech/user_service/dto/UserDto;
   #38 = NameAndType        #39:#40       // getUserById:(Ljava/lang/Long;)Lcom/smtech/user_service/dto/UserDto;
   #39 = Utf8               getUserById
   #40 = Utf8               (Ljava/lang/Long;)Lcom/smtech/user_service/dto/UserDto;
   #41 = Fieldref           #20.#42       // org/springframework/http/HttpStatus.NOT_FOUND:Lorg/springframework/http/HttpStatus;
   #42 = NameAndType        #43:#24       // NOT_FOUND:Lorg/springframework/http/HttpStatus;
   #43 = Utf8               NOT_FOUND
   #44 = Methodref          #26.#45       // org/springframework/http/ResponseEntity."<init>":(Lorg/springframework/http/HttpStatusCode;)V
   #45 = NameAndType        #5:#46        // "<init>":(Lorg/springframework/http/HttpStatusCode;)V
   #46 = Utf8               (Lorg/springframework/http/HttpStatusCode;)V
   #47 = Methodref          #26.#48       // org/springframework/http/ResponseEntity.ok:(Ljava/lang/Object;)Lorg/springframework/http/ResponseEntity;
   #48 = NameAndType        #49:#36       // ok:(Ljava/lang/Object;)Lorg/springframework/http/ResponseEntity;
   #49 = Utf8               ok
   #50 = Methodref          #14.#51       // com/smtech/user_service/service/UserService.updateUser:(JLcom/smtech/user_service/dto/UserDto;)V
   #51 = NameAndType        #52:#53       // updateUser:(JLcom/smtech/user_service/dto/UserDto;)V
   #52 = Utf8               updateUser
   #53 = Utf8               (JLcom/smtech/user_service/dto/UserDto;)V
   #54 = String             #55           // User updated
   #55 = Utf8               User updated
   #56 = Fieldref           #20.#57       // org/springframework/http/HttpStatus.OK:Lorg/springframework/http/HttpStatus;
   #57 = NameAndType        #58:#24       // OK:Lorg/springframework/http/HttpStatus;
   #58 = Utf8               OK
   #59 = Methodref          #26.#60       // org/springframework/http/ResponseEntity."<init>":(Ljava/lang/Object;Lorg/springframework/http/HttpStatusCode;)V
   #60 = NameAndType        #5:#61        // "<init>":(Ljava/lang/Object;Lorg/springframework/http/HttpStatusCode;)V
   #61 = Utf8               (Ljava/lang/Object;Lorg/springframework/http/HttpStatusCode;)V
   #62 = Class              #63           // java/lang/IllegalArgumentException
   #63 = Utf8               java/lang/IllegalArgumentException
   #64 = String             #65           // User not found
   #65 = Utf8               User not found
   #66 = Methodref          #14.#67       // com/smtech/user_service/service/UserService.deleteUserById:(J)V
   #67 = NameAndType        #68:#69       // deleteUserById:(J)V
   #68 = Utf8               deleteUserById
   #69 = Utf8               (J)V
   #70 = String             #71           // User deleted
   #71 = Utf8               User deleted
   #72 = Utf8               (Lcom/smtech/user_service/service/UserService;)V
   #73 = Utf8               Code
   #74 = Utf8               LineNumberTable
   #75 = Utf8               LocalVariableTable
   #76 = Utf8               this
   #77 = Utf8               Lcom/smtech/user_service/controller/UserController;
   #78 = Utf8               MethodParameters
   #79 = Utf8               (Lcom/smtech/user_service/dto/UserDto;)Lorg/springframework/http/ResponseEntity;
   #80 = Utf8               userDto
   #81 = Utf8               Lcom/smtech/user_service/dto/UserDto;
   #82 = Utf8               created
   #83 = Utf8               Signature
   #84 = Utf8               (Lcom/smtech/user_service/dto/UserDto;)Lorg/springframework/http/ResponseEntity<Lcom/smtech/user_service/dto/UserDto;>;
   #85 = Utf8               RuntimeVisibleAnnotations
   #86 = Utf8               Lorg/springframework/web/bind/annotation/PostMapping;
   #87 = Utf8               RuntimeVisibleParameterAnnotations
   #88 = Utf8               Lorg/springframework/web/bind/annotation/RequestBody;
   #89 = Utf8               getUser
   #90 = Utf8               (Ljava/lang/Long;)Lorg/springframework/http/ResponseEntity;
   #91 = Utf8               id
   #92 = Utf8               Ljava/lang/Long;
   #93 = Utf8               StackMapTable
   #94 = Class              #95           // com/smtech/user_service/dto/UserDto
   #95 = Utf8               com/smtech/user_service/dto/UserDto
   #96 = Utf8               (Ljava/lang/Long;)Lorg/springframework/http/ResponseEntity<Lcom/smtech/user_service/dto/UserDto;>;
   #97 = Utf8               Lorg/springframework/web/bind/annotation/GetMapping;
   #98 = Utf8               value
   #99 = Utf8               /{id}
  #100 = Utf8               Lorg/springframework/web/bind/annotation/PathVariable;
  #101 = Utf8               (JLcom/smtech/user_service/dto/UserDto;)Lorg/springframework/http/ResponseEntity;
  #102 = Utf8               e
  #103 = Utf8               Ljava/lang/IllegalArgumentException;
  #104 = Utf8               J
  #105 = Utf8               (JLcom/smtech/user_service/dto/UserDto;)Lorg/springframework/http/ResponseEntity<Ljava/lang/String;>;
  #106 = Utf8               Lorg/springframework/web/bind/annotation/PutMapping;
  #107 = Utf8               deleteUser
  #108 = Utf8               (J)Lorg/springframework/http/ResponseEntity;
  #109 = Utf8               (J)Lorg/springframework/http/ResponseEntity<Ljava/lang/String;>;
  #110 = Utf8               Lorg/springframework/web/bind/annotation/DeleteMapping;
  #111 = Utf8               SourceFile
  #112 = Utf8               UserController.java
  #113 = Utf8               Lorg/springframework/web/bind/annotation/RestController;
  #114 = Utf8               Lorg/springframework/web/bind/annotation/RequestMapping;
  #115 = Utf8               /api/v1/user
  #116 = Utf8               InnerClasses
  #117 = Utf8               BodyBuilder
{
  public com.smtech.user_service.controller.UserController(com.smtech.user_service.service.UserService);
    descriptor: (Lcom/smtech/user_service/service/UserService;)V
    flags: (0x0001) ACC_PUBLIC
    Code:
      stack=2, locals=2, args_size=2
         0: aload_0
         1: invokespecial #1                  // Method java/lang/Object."<init>":()V
         4: aload_0
         5: aload_1
         6: putfield      #7                  // Field userService:Lcom/smtech/user_service/service/UserService;
         9: return
      LineNumberTable:
        line 24: 0
        line 25: 4
        line 26: 9
      LocalVariableTable:
        Start  Length  Slot  Name   Signature
            0      10     0  this   Lcom/smtech/user_service/controller/UserController;
            0      10     1 userService   Lcom/smtech/user_service/service/UserService;
    MethodParameters:
      Name                           Flags
      userService

  public org.springframework.http.ResponseEntity<com.smtech.user_service.dto.UserDto> createUser(com.smtech.user_service.dto.UserDto);
    descriptor: (Lcom/smtech/user_service/dto/UserDto;)Lorg/springframework/http/ResponseEntity;
    flags: (0x0001) ACC_PUBLIC
    Code:
      stack=2, locals=3, args_size=2
         0: aload_0
         1: getfield      #7                  // Field userService:Lcom/smtech/user_service/service/UserService;
         4: aload_1
         5: invokevirtual #13                 // Method com/smtech/user_service/service/UserService.createUser:(Lcom/smtech/user_service/dto/UserDto;)Lcom/smtech/user_service/dto/UserDto;
         8: astore_2
         9: getstatic     #19                 // Field org/springframework/http/HttpStatus.CREATED:Lorg/springframework/http/HttpStatus;
        12: invokestatic  #25                 // Method org/springframework/http/ResponseEntity.status:(Lorg/springframework/http/HttpStatusCode;)Lorg/springframework/http/ResponseEntity$BodyBuilder;
        15: aload_2
        16: invokeinterface #31,  2           // InterfaceMethod org/springframework/http/ResponseEntity$BodyBuilder.body:(Ljava/lang/Object;)Lorg/springframework/http/ResponseEntity;
        21: areturn
      LineNumberTable:
        line 30: 0
        line 31: 9
      LocalVariableTable:
        Start  Length  Slot  Name   Signature
            0      22     0  this   Lcom/smtech/user_service/controller/UserController;
            0      22     1 userDto   Lcom/smtech/user_service/dto/UserDto;
            9      13     2 created   Lcom/smtech/user_service/dto/UserDto;
    MethodParameters:
      Name                           Flags
      userDto
    Signature: #84                          // (Lcom/smtech/user_service/dto/UserDto;)Lorg/springframework/http/ResponseEntity<Lcom/smtech/user_service/dto/UserDto;>;
    RuntimeVisibleAnnotations:
      0: #86()
        org.springframework.web.bind.annotation.PostMapping
    RuntimeVisibleParameterAnnotations:
      parameter 0:
        0: #88()
          org.springframework.web.bind.annotation.RequestBody

  public org.springframework.http.ResponseEntity<com.smtech.user_service.dto.UserDto> getUser(java.lang.Long);
    descriptor: (Ljava/lang/Long;)Lorg/springframework/http/ResponseEntity;
    flags: (0x0001) ACC_PUBLIC
    Code:
      stack=3, locals=3, args_size=2
         0: aload_0
         1: getfield      #7                  // Field userService:Lcom/smtech/user_service/service/UserService;
         4: aload_1
         5: invokevirtual #37                 // Method com/smtech/user_service/service/UserService.getUserById:(Ljava/lang/Long;)Lcom/smtech/user_service/dto/UserDto;
         8: astore_2
         9: aload_2
        10: ifnonnull     24
        13: new           #26                 // class org/springframework/http/ResponseEntity
        16: dup
        17: getstatic     #41                 // Field org/springframework/http/HttpStatus.NOT_FOUND:Lorg/springframework/http/HttpStatus;
        20: invokespecial #44                 // Method org/springframework/http/ResponseEntity."<init>":(Lorg/springframework/http/HttpStatusCode;)V
        23: areturn
        24: aload_2
        25: invokestatic  #47                 // Method org/springframework/http/ResponseEntity.ok:(Ljava/lang/Object;)Lorg/springframework/http/ResponseEntity;
        28: areturn
      LineNumberTable:
        line 36: 0
        line 38: 9
        line 39: 13
        line 41: 24
      LocalVariableTable:
        Start  Length  Slot  Name   Signature
            0      29     0  this   Lcom/smtech/user_service/controller/UserController;
            0      29     1    id   Ljava/lang/Long;
            9      20     2 userDto   Lcom/smtech/user_service/dto/UserDto;
      StackMapTable: number_of_entries = 1
        frame_type = 252 /* append */
          offset_delta = 24
          locals = [ class com/smtech/user_service/dto/UserDto ]
    MethodParameters:
      Name                           Flags
      id
    Signature: #96                          // (Ljava/lang/Long;)Lorg/springframework/http/ResponseEntity<Lcom/smtech/user_service/dto/UserDto;>;
    RuntimeVisibleAnnotations:
      0: #97(#98=[s#99])
        org.springframework.web.bind.annotation.GetMapping(
          value=["/{id}"]
        )
    RuntimeVisibleParameterAnnotations:
      parameter 0:
        0: #100()
          org.springframework.web.bind.annotation.PathVariable

  public org.springframework.http.ResponseEntity<java.lang.String> updateUser(long, com.smtech.user_service.dto.UserDto);
    descriptor: (JLcom/smtech/user_service/dto/UserDto;)Lorg/springframework/http/ResponseEntity;
    flags: (0x0001) ACC_PUBLIC
    Code:
      stack=4, locals=5, args_size=3
         0: aload_0
         1: getfield      #7                  // Field userService:Lcom/smtech/user_service/service/UserService;
         4: lload_1
         5: aload_3
         6: invokevirtual #50                 // Method com/smtech/user_service/service/UserService.updateUser:(JLcom/smtech/user_service/dto/UserDto;)V
         9: new           #26                 // class org/springframework/http/ResponseEntity
        12: dup
        13: ldc           #54                 // String User updated
        15: getstatic     #56                 // Field org/springframework/http/HttpStatus.OK:Lorg/springframework/http/HttpStatus;
        18: invokespecial #59                 // Method org/springframework/http/ResponseEntity."<init>":(Ljava/lang/Object;Lorg/springframework/http/HttpStatusCode;)V
        21: areturn
        22: astore        4
        24: new           #26                 // class org/springframework/http/ResponseEntity
        27: dup
        28: ldc           #64                 // String User not found
        30: getstatic     #41                 // Field org/springframework/http/HttpStatus.NOT_FOUND:Lorg/springframework/http/HttpStatus;
        33: invokespecial #59                 // Method org/springframework/http/ResponseEntity."<init>":(Ljava/lang/Object;Lorg/springframework/http/HttpStatusCode;)V
        36: areturn
      Exception table:
         from    to  target type
             0    21    22   Class java/lang/IllegalArgumentException
      LineNumberTable:
        line 47: 0
        line 48: 9
        line 49: 22
        line 50: 24
      LocalVariableTable:
        Start  Length  Slot  Name   Signature
           24      13     4     e   Ljava/lang/IllegalArgumentException;
            0      37     0  this   Lcom/smtech/user_service/controller/UserController;
            0      37     1    id   J
            0      37     3 userDto   Lcom/smtech/user_service/dto/UserDto;
      StackMapTable: number_of_entries = 1
        frame_type = 86 /* same_locals_1_stack_item */
          stack = [ class java/lang/IllegalArgumentException ]
    MethodParameters:
      Name                           Flags
      id
      userDto
    Signature: #105                         // (JLcom/smtech/user_service/dto/UserDto;)Lorg/springframework/http/ResponseEntity<Ljava/lang/String;>;
    RuntimeVisibleAnnotations:
      0: #106(#98=[s#99])
        org.springframework.web.bind.annotation.PutMapping(
          value=["/{id}"]
        )
    RuntimeVisibleParameterAnnotations:
      parameter 0:
        0: #100()
          org.springframework.web.bind.annotation.PathVariable
      parameter 1:
        0: #88()
          org.springframework.web.bind.annotation.RequestBody

  public org.springframework.http.ResponseEntity<java.lang.String> deleteUser(long);
    descriptor: (J)Lorg/springframework/http/ResponseEntity;
    flags: (0x0001) ACC_PUBLIC
    Code:
      stack=4, locals=4, args_size=2
         0: aload_0
         1: getfield      #7                  // Field userService:Lcom/smtech/user_service/service/UserService;
         4: lload_1
         5: invokevirtual #66                 // Method com/smtech/user_service/service/UserService.deleteUserById:(J)V
         8: new           #26                 // class org/springframework/http/ResponseEntity
        11: dup
        12: ldc           #70                 // String User deleted
        14: getstatic     #56                 // Field org/springframework/http/HttpStatus.OK:Lorg/springframework/http/HttpStatus;
        17: invokespecial #59                 // Method org/springframework/http/ResponseEntity."<init>":(Ljava/lang/Object;Lorg/springframework/http/HttpStatusCode;)V
        20: areturn
        21: astore_3
        22: new           #26                 // class org/springframework/http/ResponseEntity
        25: dup
        26: ldc           #64                 // String User not found
        28: getstatic     #41                 // Field org/springframework/http/HttpStatus.NOT_FOUND:Lorg/springframework/http/HttpStatus;
        31: invokespecial #59                 // Method org/springframework/http/ResponseEntity."<init>":(Ljava/lang/Object;Lorg/springframework/http/HttpStatusCode;)V
        34: areturn
      Exception table:
         from    to  target type
             0    20    21   Class java/lang/IllegalArgumentException
      LineNumberTable:
        line 57: 0
        line 58: 8
        line 59: 21
        line 60: 22
      LocalVariableTable:
        Start  Length  Slot  Name   Signature
           22      13     3     e   Ljava/lang/IllegalArgumentException;
            0      35     0  this   Lcom/smtech/user_service/controller/UserController;
            0      35     1    id   J
      StackMapTable: number_of_entries = 1
        frame_type = 85 /* same_locals_1_stack_item */
          stack = [ class java/lang/IllegalArgumentException ]
    MethodParameters:
      Name                           Flags
      id
    Signature: #109                         // (J)Lorg/springframework/http/ResponseEntity<Ljava/lang/String;>;
    RuntimeVisibleAnnotations:
      0: #110(#98=[s#99])
        org.springframework.web.bind.annotation.DeleteMapping(
          value=["/{id}"]
        )
    RuntimeVisibleParameterAnnotations:
      parameter 0:
        0: #100()
          org.springframework.web.bind.annotation.PathVariable
}
SourceFile: "UserController.java"
RuntimeVisibleAnnotations:
  0: #113()
    org.springframework.web.bind.annotation.RestController
  1: #114(#98=[s#115])
    org.springframework.web.bind.annotation.RequestMapping(
      value=["/api/v1/user"]
    )
InnerClasses:
  public static #117= #32 of #26;         // BodyBuilder=class org/springframework/http/ResponseEntity$BodyBuilder of class org/springframework/http/ResponseEntity
